{
  "description": "Toronto Maple Leafs season statistics 2014-15 through 2023-24",
  "source": "Compiled from NHL.com, Hockey-Reference.com, HockeyFights.com",
  "team": "Toronto Maple Leafs",
  "seasons": [
    {
      "season": "2014-15",
      "wins": 30,
      "losses": 44,
      "ot_losses": 8,
      "points": 68,
      "goals_for": 211,
      "goals_against": 262,
      "home_wins": 17,
      "home_losses": 19,
      "home_ot": 5,
      "away_wins": 13,
      "away_losses": 25,
      "away_ot": 3,
      "fights": 32,
      "playoff_result": "Missed playoffs",
      "top_scorer": {"name": "Phil Kessel", "goals": 25, "assists": 36, "points": 61},
      "top_goal_scorer": {"name": "James van Riemsdyk", "goals": 27},
      "notes": "Disastrous season led to rebuild. Coach Randy Carlyle fired mid-season."
    },
    {
      "season": "2015-16",
      "wins": 29,
      "losses": 42,
      "ot_losses": 11,
      "points": 69,
      "goals_for": 198,
      "goals_against": 246,
      "home_wins": 16,
      "home_losses": 20,
      "home_ot": 5,
      "away_wins": 13,
      "away_losses": 22,
      "away_ot": 6,
      "fights": 28,
      "playoff_result": "Missed playoffs",
      "top_scorer": {"name": "Nazem Kadri", "goals": 17, "assists": 28, "points": 45},
      "top_goal_scorer": {"name": "Nazem Kadri", "goals": 17},
      "notes": "Tank season. Auston Matthews drafted 1st overall. Mike Babcock's first year."
    },
    {
      "season": "2016-17",
      "wins": 40,
      "losses": 27,
      "ot_losses": 15,
      "points": 95,
      "goals_for": 251,
      "goals_against": 242,
      "home_wins": 22,
      "home_losses": 12,
      "home_ot": 7,
      "away_wins": 18,
      "away_losses": 15,
      "away_ot": 8,
      "fights": 22,
      "playoff_result": "Lost Round 1 vs Washington (4-2)",
      "top_scorer": {"name": "Auston Matthews", "goals": 40, "assists": 29, "points": 69},
      "top_goal_scorer": {"name": "Auston Matthews", "goals": 40},
      "notes": "Rookie sensations: Matthews (40G), Marner (61pts), Nylander (61pts). First playoffs since 2013."
    },
    {
      "season": "2017-18",
      "wins": 49,
      "losses": 26,
      "ot_losses": 7,
      "points": 105,
      "goals_for": 277,
      "goals_against": 232,
      "home_wins": 29,
      "home_losses": 10,
      "home_ot": 2,
      "away_wins": 20,
      "away_losses": 16,
      "away_ot": 5,
      "fights": 18,
      "playoff_result": "Lost Round 1 vs Boston (4-3)",
      "top_scorer": {"name": "Mitch Marner", "goals": 22, "assists": 47, "points": 69},
      "top_goal_scorer": {"name": "Auston Matthews", "goals": 34},
      "notes": "Franchise record 49 wins. Heartbreaking Game 7 loss to Boston."
    },
    {
      "season": "2018-19",
      "wins": 46,
      "losses": 28,
      "ot_losses": 8,
      "points": 100,
      "goals_for": 286,
      "goals_against": 251,
      "home_wins": 26,
      "home_losses": 12,
      "home_ot": 3,
      "away_wins": 20,
      "away_losses": 16,
      "away_ot": 5,
      "fights": 15,
      "playoff_result": "Lost Round 1 vs Boston (4-3)",
      "top_scorer": {"name": "Mitch Marner", "goals": 26, "assists": 68, "points": 94},
      "top_goal_scorer": {"name": "John Tavares", "goals": 47},
      "notes": "John Tavares signed as free agent. Another Game 7 loss to Boston."
    },
    {
      "season": "2019-20",
      "wins": 36,
      "losses": 25,
      "ot_losses": 9,
      "points": 81,
      "goals_for": 238,
      "goals_against": 227,
      "home_wins": 19,
      "home_losses": 12,
      "home_ot": 4,
      "away_wins": 17,
      "away_losses": 13,
      "away_ot": 5,
      "fights": 11,
      "playoff_result": "Lost Play-In vs Columbus (3-2)",
      "top_scorer": {"name": "Auston Matthews", "goals": 47, "assists": 33, "points": 80},
      "top_goal_scorer": {"name": "Auston Matthews", "goals": 47},
      "notes": "COVID-shortened season (70 games). Babcock fired Nov 2019, Sheldon Keefe took over."
    },
    {
      "season": "2020-21",
      "wins": 35,
      "losses": 14,
      "ot_losses": 7,
      "points": 77,
      "goals_for": 187,
      "goals_against": 148,
      "home_wins": 18,
      "home_losses": 8,
      "home_ot": 2,
      "away_wins": 17,
      "away_losses": 6,
      "away_ot": 5,
      "fights": 9,
      "playoff_result": "Lost Round 1 vs Montreal (4-3)",
      "top_scorer": {"name": "Auston Matthews", "goals": 41, "assists": 25, "points": 66},
      "top_goal_scorer": {"name": "Auston Matthews", "goals": 41},
      "notes": "56-game COVID season in all-Canadian North Division. Won division but choked vs Montreal."
    },
    {
      "season": "2021-22",
      "wins": 54,
      "losses": 21,
      "ot_losses": 7,
      "points": 115,
      "goals_for": 312,
      "goals_against": 252,
      "home_wins": 29,
      "home_losses": 9,
      "home_ot": 3,
      "away_wins": 25,
      "away_losses": 12,
      "away_ot": 4,
      "fights": 12,
      "playoff_result": "Lost Round 1 vs Tampa Bay (4-3)",
      "top_scorer": {"name": "Auston Matthews", "goals": 60, "assists": 46, "points": 106},
      "top_goal_scorer": {"name": "Auston Matthews", "goals": 60},
      "notes": "Matthews won Hart Trophy (MVP) and Rocket Richard. Franchise record 54 wins, 115 points."
    },
    {
      "season": "2022-23",
      "wins": 50,
      "losses": 21,
      "ot_losses": 11,
      "points": 111,
      "goals_for": 287,
      "goals_against": 222,
      "home_wins": 27,
      "home_losses": 10,
      "home_ot": 4,
      "away_wins": 23,
      "away_losses": 11,
      "away_ot": 7,
      "fights": 14,
      "playoff_result": "Won Round 1 vs Tampa Bay (4-2), Lost Round 2 vs Florida (4-1)",
      "top_scorer": {"name": "Mitch Marner", "goals": 28, "assists": 57, "points": 85},
      "top_goal_scorer": {"name": "Auston Matthews", "goals": 40},
      "notes": "Finally won a playoff round! First series win since 2004. Lost to eventual Cup finalist Florida."
    },
    {
      "season": "2023-24",
      "wins": 46,
      "losses": 26,
      "ot_losses": 10,
      "points": 102,
      "goals_for": 298,
      "goals_against": 261,
      "home_wins": 25,
      "home_losses": 13,
      "home_ot": 3,
      "away_wins": 21,
      "away_losses": 13,
      "away_ot": 7,
      "fights": 25,
      "playoff_result": "Lost Round 1 vs Boston (4-3)",
      "top_scorer": {"name": "Auston Matthews", "goals": 69, "assists": 38, "points": 107},
      "top_goal_scorer": {"name": "Auston Matthews", "goals": 69},
      "notes": "Matthews set franchise record with 69 goals! Yet another Game 7 loss to Boston."
    }
  ]
}
